operatedb/__init__.py
operatedb/operatedb.py
operatedb/updatetable.py
operatedb-0.0.1.dist-info/DESCRIPTION.rst
operatedb-0.0.1.dist-info/METADATA
operatedb-0.0.1.dist-info/RECORD
operatedb-0.0.1.dist-info/WHEEL
operatedb-0.0.1.dist-info/metadata.json
operatedb-0.0.1.dist-info/top_level.txt
